lint_po/__init__.py
lint_po/main.py
lint_po-0.1.4.data/scripts/lint-po
lint_po-0.1.4.dist-info/LICENSE
lint_po-0.1.4.dist-info/METADATA
lint_po-0.1.4.dist-info/WHEEL
lint_po-0.1.4.dist-info/top_level.txt
lint_po-0.1.4.dist-info/RECORD
