Metadata-Version: 2.1
Name: lint-po
Version: 0.1.4
Summary: A simple gettext .po linter to check for mangled variable names in translations
Home-page: https://github.com/himdel/lint-po
License: Apache License 2.0
License-File: LICENSE
